LICENSE.md
MANIFEST.in
README.md
pyproject.toml
setup.cfg
setup.py
killMS/AQWeight.py
killMS/BLCal.py
killMS/CMakeLists.txt
killMS/ClipCal.py
killMS/InterpSols.py
killMS/MakePlotMovie.py
killMS/MergeSols.py
killMS/PlotSols.py
killMS/PlotSolsIm.py
killMS/SmoothSols.py
killMS/TestSpeedNp.py
killMS/__init__.py
killMS/dsc.py
killMS/grepall.py
killMS/kMS.py
killMS.egg-info/PKG-INFO
killMS.egg-info/SOURCES.txt
killMS.egg-info/dependency_links.txt
killMS.egg-info/not-zip-safe
killMS.egg-info/requires.txt
killMS.egg-info/top_level.txt
killMS/Array/CMakeLists.txt
killMS/Array/ModLinAlg.py
killMS/Array/NpShared.py
killMS/Array/RecArrayOps.py
killMS/Array/__init__.py
killMS/Array/Dot/CMakeLists.txt
killMS/Array/Dot/NpCuda.py
killMS/Array/Dot/NpDotSSE.py
killMS/Array/Dot/TestDotSSE.py
killMS/Array/Dot/__init__.py
killMS/Array/Dot/dotSSE.h
killMS/Data/ClassBeam.py
killMS/Data/ClassJonesDomains.py
killMS/Data/ClassMS.py
killMS/Data/ClassReCluster.py
killMS/Data/ClassVisServer.py
killMS/Data/ClassWeighting.py
killMS/Data/__init__.py
killMS/Data/sidereal.py
killMS/Gridder/CMakeLists.txt
killMS/Gridder/Gridder.h
killMS/Gridder/__init__.py
killMS/Other/ClassClip.py
killMS/Other/ClassFitAmp.py
killMS/Other/ClassFitTEC.py
killMS/Other/ClassPrint.py
killMS/Other/ClassTimeIt.py
killMS/Other/Counter.py
killMS/Other/ModChanEquidistant.py
killMS/Other/ModColor.py
killMS/Other/ModParsetType.py
killMS/Other/MyPickle.py
killMS/Other/PrintOptParse.py
killMS/Other/__init__.py
killMS/Other/findrms.py
killMS/Other/least_squares.py
killMS/Other/logo.py
killMS/Other/rad2hmsdms.py
killMS/Other/reformat.py
killMS/Parset/ClassPrint.py
killMS/Parset/DefaultParset.cfg
killMS/Parset/MyOptParse.py
killMS/Parset/PrintOptParse.py
killMS/Parset/ReadCFG.py
killMS/Parset/__init__.py
killMS/Plot/GiveNXNYPanels.py
killMS/Plot/GiveRectSubplot.py
killMS/Plot/Graph.py
killMS/Plot/__init__.py
killMS/Predict/CMakeLists.txt
killMS/Predict/ClassImageSM2.py
killMS/Predict/PredictGaussPoints_NumExpr.py
killMS/Predict/PredictGaussPoints_NumExpr5.py
killMS/Predict/__init__.py
killMS/Predict/predict.c
killMS/Predict/predict.h
killMS/Simul/DoSimul.py
killMS/Simul/MakeClusterCat.py
