Metadata-Version: 2.1
Name: killMS
Version: 3.1.0
Summary: A Wirtinger-based direction-dependent radio interferometric calibration package
Home-page: http://github.com/saopicc/killMS
Author: Cyril Tasse
Author-email: cyril.tasse@obspm.fr
License: GNU GPL v2
Platform: UNKNOWN
Classifier: Development Status :: 4 - Beta
Classifier: Environment :: Console
Classifier: Intended Audience :: Science/Research
Classifier: License :: OSI Approved :: GNU General Public License v2 (GPLv2)
Classifier: Operating System :: POSIX :: Linux
Classifier: Programming Language :: Python
Classifier: Topic :: Scientific/Engineering :: Astronomy
Requires-Python: >=3.0,<3.9
Provides-Extra: fits-beam-support
License-File: LICENSE.md
